jpar/parser.py
src/pretty_parser.py
jpar-0.0.1.dist-info/METADATA
jpar-0.0.1.dist-info/WHEEL
jpar-0.0.1.dist-info/top_level.txt
jpar-0.0.1.dist-info/RECORD
