Metadata-Version: 2.1
Name: jpar
Version: 0.0.1
Summary: This tool helps to show the json data collected from different sources in a single format.
Home-page: https://github.com/ferdielik/jpar
Author: Ferdi Elik
Author-email: elikferdi@gmail.com
License: Apache2
Platform: UNKNOWN
Classifier: Development Status :: 4 - Beta
Classifier: Intended Audience :: System Administrators
Classifier: License :: OSI Approved :: Apache Software License
Classifier: Programming Language :: Python :: 3
